DeepFV/FisherVectorDL.py
DeepFV/__init__.py
deepfv-0.2.10.dist-info/licenses/LICENSE
deepfv-0.2.10.dist-info/METADATA
deepfv-0.2.10.dist-info/WHEEL
deepfv-0.2.10.dist-info/top_level.txt
deepfv-0.2.10.dist-info/RECORD
