Metadata-Version: 2.4
Name: DeepFV
Version: 0.2.10
Summary: Fisher Vectors based on Gaussian Mixture Model with TensorFlow deep learning support
Home-page: https://github.com/sidhomj/DeepFV
Author: John-William Sidhom
Author-email: 
Maintainer: John-William Sidhom
License: MIT
Keywords: fisher-vectors,gaussian-mixture-model,deep-learning,tensorflow,computer-vision
Classifier: Development Status :: 4 - Beta
Classifier: Intended Audience :: Science/Research
Classifier: License :: OSI Approved :: MIT License
Classifier: Programming Language :: Python :: 3
Classifier: Programming Language :: Python :: 3.6
Classifier: Programming Language :: Python :: 3.7
Classifier: Programming Language :: Python :: 3.8
Classifier: Programming Language :: Python :: 3.9
Classifier: Programming Language :: Python :: 3.10
Classifier: Topic :: Scientific/Engineering :: Artificial Intelligence
Classifier: Topic :: Scientific/Engineering :: Image Recognition
Requires-Python: >=3.6
License-File: LICENSE
Requires-Dist: numpy>=1.13.3
Requires-Dist: scipy
Requires-Dist: scikit-learn>=0.24.0
Requires-Dist: tensorflow>=2.0.0
Requires-Dist: matplotlib>=3.0.0
Dynamic: author
Dynamic: classifier
Dynamic: description
Dynamic: description-content-type
Dynamic: home-page
Dynamic: keywords
Dynamic: license
Dynamic: license-file
Dynamic: maintainer
Dynamic: requires-dist
Dynamic: requires-python
Dynamic: summary
